minihuman/__init__.py
minihuman/application/__init__.py
minihuman/application/education/__init__.py
minihuman/application/education/knowledge_tracing/__init__.py
minihuman/application/education/knowledge_tracing/RKT/TIR.py
minihuman/application/education/knowledge_tracing/RKT/__init__.py
minihuman/application/education/knowledge_tracing/RKT/experiment.py
minihuman/application/education/knowledge_tracing/RKT/llm_api.py
minihuman/application/education/knowledge_tracing/RKT/lm_classifier.py
minihuman/application/education/knowledge_tracing/RKT/utils.py
minihuman/application/hci/__init__.py
minihuman/application/hci/multi_agent_colab/__init__.py
minihuman/application/hci/multi_agent_colab/brainstorm/__init__.py
minihuman/application/hci/multi_agent_colab/brainstorm/brainstorm.py
minihuman/application/hci/user_experience/__init__.py
minihuman/application/hci/user_experience/survey_research/__init__.py
minihuman/application/hci/user_experience/survey_research/demo.py
minihuman/application/hci/user_experience/survey_research/llm_api.py
minihuman/application/hci/user_experience/survey_research/survey_study.py
minihuman/behavior/__init__.py
minihuman/dataloader/__init__.py
minihuman/environment/__init__.py
minihuman/models/__init__.py
minihuman/models/demo.py
minihuman/models/lm_classifier.py
minihuman/models/text_cluster.py
minihuman/utils/__init__.py
minihuman/utils_llm/__init__.py
minihuman/utils_rl/__init__.py
minihuman-0.2.1.dist-info/LICENSE
minihuman-0.2.1.dist-info/METADATA
minihuman-0.2.1.dist-info/WHEEL
minihuman-0.2.1.dist-info/top_level.txt
minihuman-0.2.1.dist-info/RECORD
