Metadata-Version: 2.1
Name: minihuman
Version: 0.2.1
Summary: MiniHuman: A Python Library to Simulate Virtual Human Behaviors and Responses to Environmental Stimuli
Author: human.ai.integration
Author-email: human.ai.integration@gmail.com
Project-URL: Bug Tracker, https://github.com/songlinxu/MiniHuman-Toolkit
Classifier: Programming Language :: Python :: 3
Classifier: License :: OSI Approved :: MIT License
Classifier: Operating System :: OS Independent
Requires-Python: >=3.5
License-File: LICENSE
Requires-Dist: numpy>=1.17.2
Requires-Dist: pandas>=1.1.5
Requires-Dist: scikit-learn
